fast_unit-0.5.1.dist-info/METADATA
fast_unit-0.5.1.dist-info/WHEEL
fast_unit/fast_unit.pyi
fast_unit/__pycache__/__init__.cpython-310.pyc
fast_unit/__pycache__/units.cpython-310.pyc
fast_unit/py.typed
fast_unit/units.py
fast_unit/__init__.py
fast_unit/fast_unit.cpython-36m-x86_64-linux-gnu.so
fast_unit-0.5.1.dist-info/RECORD
