Metadata-Version: 2.1
Name: fast_unit
Version: 0.5.1
